villonaco/__init__.py
villonaco/main.py
villonaco-0.1.0.dist-info/WHEEL
villonaco-0.1.0.dist-info/METADATA
villonaco-0.1.0.dist-info/RECORD
